<annotation>
	<folder>bmp</folder>
	<filename>000120.bmp</filename>
	<path>C:\Users\13676\Desktop\cell_dataset\bmp\000120.bmp</path>
	<source>
		<database>Unknown</database>
	</source>
	<size>
		<width>2592</width>
		<height>1944</height>
		<depth>3</depth>
	</size>
	<segmented>0</segmented>
	<object>
		<name>23</name>
		<pose>Unspecified</pose>
		<truncated>0</truncated>
		<difficult>0</difficult>
		<bndbox>
			<xmin>116</xmin>
			<ymin>1107</ymin>
			<xmax>326</xmax>
			<ymax>1316</ymax>
		</bndbox>
	</object>
	<object>
		<name>24</name>
		<pose>Unspecified</pose>
		<truncated>0</truncated>
		<difficult>0</difficult>
		<bndbox>
			<xmin>248</xmin>
			<ymin>1675</ymin>
			<xmax>433</xmax>
			<ymax>1853</ymax>
		</bndbox>
	</object>
	<object>
		<name>23</name>
		<pose>Unspecified</pose>
		<truncated>0</truncated>
		<difficult>0</difficult>
		<bndbox>
			<xmin>575</xmin>
			<ymin>870</ymin>
			<xmax>858</xmax>
			<ymax>1119</ymax>
		</bndbox>
	</object>
	<object>
		<name>24</name>
		<pose>Unspecified</pose>
		<truncated>0</truncated>
		<difficult>0</difficult>
		<bndbox>
			<xmin>736</xmin>
			<ymin>653</ymin>
			<xmax>936</xmax>
			<ymax>851</ymax>
		</bndbox>
	</object>
	<object>
		<name>23</name>
		<pose>Unspecified</pose>
		<truncated>0</truncated>
		<difficult>0</difficult>
		<bndbox>
			<xmin>1336</xmin>
			<ymin>851</ymin>
			<xmax>1536</xmax>
			<ymax>1060</ymax>
		</bndbox>
	</object>
	<object>
		<name>23</name>
		<pose>Unspecified</pose>
		<truncated>0</truncated>
		<difficult>0</difficult>
		<bndbox>
			<xmin>1340</xmin>
			<ymin>1165</ymin>
			<xmax>1533</xmax>
			<ymax>1370</ymax>
		</bndbox>
	</object>
</annotation>