<annotation>
	<folder>JPEGImage</folder>
	<filename>cui2021-06-03-14.jpg</filename>
	<path>C:\Users\13676\Desktop\2021-06-03\reorganize\JPEGImage\cui2021-06-03-14.jpg</path>
	<source>
		<database>Unknown</database>
	</source>
	<size>
		<width>2448</width>
		<height>2048</height>
		<depth>3</depth>
	</size>
	<segmented>0</segmented>
	<object>
		<name>23</name>
		<pose>Unspecified</pose>
		<truncated>0</truncated>
		<difficult>0</difficult>
		<bndbox>
			<xmin>105</xmin>
			<ymin>620</ymin>
			<xmax>294</xmax>
			<ymax>818</ymax>
		</bndbox>
	</object>
	<object>
		<name>3</name>
		<pose>Unspecified</pose>
		<truncated>0</truncated>
		<difficult>0</difficult>
		<bndbox>
			<xmin>439</xmin>
			<ymin>526</ymin>
			<xmax>768</xmax>
			<ymax>747</ymax>
		</bndbox>
	</object>
	<object>
		<name>x</name>
		<pose>Unspecified</pose>
		<truncated>0</truncated>
		<difficult>0</difficult>
		<bndbox>
			<xmin>467</xmin>
			<ymin>254</ymin>
			<xmax>764</xmax>
			<ymax>481</ymax>
		</bndbox>
	</object>
	<object>
		<name>24</name>
		<pose>Unspecified</pose>
		<truncated>0</truncated>
		<difficult>0</difficult>
		<bndbox>
			<xmin>576</xmin>
			<ymin>696</ymin>
			<xmax>739</xmax>
			<ymax>872</ymax>
		</bndbox>
	</object>
	<object>
		<name>6</name>
		<pose>Unspecified</pose>
		<truncated>0</truncated>
		<difficult>0</difficult>
		<bndbox>
			<xmin>114</xmin>
			<ymin>1715</ymin>
			<xmax>357</xmax>
			<ymax>1970</ymax>
		</bndbox>
	</object>
	<object>
		<name>42</name>
		<pose>Unspecified</pose>
		<truncated>0</truncated>
		<difficult>0</difficult>
		<bndbox>
			<xmin>347</xmin>
			<ymin>1709</ymin>
			<xmax>578</xmax>
			<ymax>1949</ymax>
		</bndbox>
	</object>
	<object>
		<name>23</name>
		<pose>Unspecified</pose>
		<truncated>0</truncated>
		<difficult>0</difficult>
		<bndbox>
			<xmin>431</xmin>
			<ymin>1325</ymin>
			<xmax>638</xmax>
			<ymax>1536</ymax>
		</bndbox>
	</object>
	<object>
		<name>6</name>
		<pose>Unspecified</pose>
		<truncated>0</truncated>
		<difficult>0</difficult>
		<bndbox>
			<xmin>884</xmin>
			<ymin>886</ymin>
			<xmax>1139</xmax>
			<ymax>1126</ymax>
		</bndbox>
	</object>
	<object>
		<name>23</name>
		<pose>Unspecified</pose>
		<truncated>0</truncated>
		<difficult>0</difficult>
		<bndbox>
			<xmin>1130</xmin>
			<ymin>638</ymin>
			<xmax>1323</xmax>
			<ymax>820</ymax>
		</bndbox>
	</object>
	<object>
		<name>6</name>
		<pose>Unspecified</pose>
		<truncated>0</truncated>
		<difficult>0</difficult>
		<bndbox>
			<xmin>1355</xmin>
			<ymin>949</ymin>
			<xmax>1549</xmax>
			<ymax>1159</ymax>
		</bndbox>
	</object>
	<object>
		<name>32</name>
		<pose>Unspecified</pose>
		<truncated>0</truncated>
		<difficult>0</difficult>
		<bndbox>
			<xmin>1733</xmin>
			<ymin>1505</ymin>
			<xmax>1878</xmax>
			<ymax>1660</ymax>
		</bndbox>
	</object>
	<object>
		<name>23</name>
		<pose>Unspecified</pose>
		<truncated>0</truncated>
		<difficult>0</difficult>
		<bndbox>
			<xmin>1576</xmin>
			<ymin>1826</ymin>
			<xmax>1725</xmax>
			<ymax>1999</ymax>
		</bndbox>
	</object>
	<object>
		<name>5</name>
		<pose>Unspecified</pose>
		<truncated>0</truncated>
		<difficult>0</difficult>
		<bndbox>
			<xmin>1883</xmin>
			<ymin>325</ymin>
			<xmax>2176</xmax>
			<ymax>586</ymax>
		</bndbox>
	</object>
	<object>
		<name>5</name>
		<pose>Unspecified</pose>
		<truncated>0</truncated>
		<difficult>0</difficult>
		<bndbox>
			<xmin>1872</xmin>
			<ymin>564</ymin>
			<xmax>2168</xmax>
			<ymax>831</ymax>
		</bndbox>
	</object>
	<object>
		<name>32</name>
		<pose>Unspecified</pose>
		<truncated>0</truncated>
		<difficult>0</difficult>
		<bndbox>
			<xmin>1725</xmin>
			<ymin>493</ymin>
			<xmax>1909</xmax>
			<ymax>691</ymax>
		</bndbox>
	</object>
	<object>
		<name>6</name>
		<pose>Unspecified</pose>
		<truncated>0</truncated>
		<difficult>0</difficult>
		<bndbox>
			<xmin>1975</xmin>
			<ymin>960</ymin>
			<xmax>2215</xmax>
			<ymax>1207</ymax>
		</bndbox>
	</object>
</annotation>
