<annotation>
	<folder>JPEGImage</folder>
	<filename>cui2021-06-03-2.jpg</filename>
	<path>C:\Users\13676\Desktop\2021-06-03\reorganize\JPEGImage\cui2021-06-03-2.jpg</path>
	<source>
		<database>Unknown</database>
	</source>
	<size>
		<width>2448</width>
		<height>2048</height>
		<depth>3</depth>
	</size>
	<segmented>0</segmented>
	<object>
		<name>23</name>
		<pose>Unspecified</pose>
		<truncated>0</truncated>
		<difficult>0</difficult>
		<bndbox>
			<xmin>211</xmin>
			<ymin>689</ymin>
			<xmax>418</xmax>
			<ymax>876</ymax>
		</bndbox>
	</object>
	<object>
		<name>23</name>
		<pose>Unspecified</pose>
		<truncated>0</truncated>
		<difficult>0</difficult>
		<bndbox>
			<xmin>526</xmin>
			<ymin>1116</ymin>
			<xmax>724</xmax>
			<ymax>1314</ymax>
		</bndbox>
	</object>
	<object>
		<name>3</name>
		<pose>Unspecified</pose>
		<truncated>0</truncated>
		<difficult>0</difficult>
		<bndbox>
			<xmin>328</xmin>
			<ymin>1578</ymin>
			<xmax>614</xmax>
			<ymax>1955</ymax>
		</bndbox>
	</object>
	<object>
		<name>1</name>
		<pose>Unspecified</pose>
		<truncated>0</truncated>
		<difficult>0</difficult>
		<bndbox>
			<xmin>328</xmin>
			<ymin>1228</ymin>
			<xmax>695</xmax>
			<ymax>1649</ymax>
		</bndbox>
	</object>
	<object>
		<name>6</name>
		<pose>Unspecified</pose>
		<truncated>0</truncated>
		<difficult>0</difficult>
		<bndbox>
			<xmin>611</xmin>
			<ymin>1230</ymin>
			<xmax>886</xmax>
			<ymax>1512</ymax>
		</bndbox>
	</object>
	<object>
		<name>32</name>
		<pose>Unspecified</pose>
		<truncated>0</truncated>
		<difficult>0</difficult>
		<bndbox>
			<xmin>849</xmin>
			<ymin>1128</ymin>
			<xmax>1024</xmax>
			<ymax>1301</ymax>
		</bndbox>
	</object>
	<object>
		<name>5</name>
		<pose>Unspecified</pose>
		<truncated>0</truncated>
		<difficult>0</difficult>
		<bndbox>
			<xmin>841</xmin>
			<ymin>512</ymin>
			<xmax>1189</xmax>
			<ymax>824</ymax>
		</bndbox>
	</object>
	<object>
		<name>24</name>
		<pose>Unspecified</pose>
		<truncated>0</truncated>
		<difficult>0</difficult>
		<bndbox>
			<xmin>1493</xmin>
			<ymin>255</ymin>
			<xmax>1699</xmax>
			<ymax>491</ymax>
		</bndbox>
	</object>
	<object>
		<name>x</name>
		<pose>Unspecified</pose>
		<truncated>0</truncated>
		<difficult>0</difficult>
		<bndbox>
			<xmin>1262</xmin>
			<ymin>647</ymin>
			<xmax>1516</xmax>
			<ymax>897</ymax>
		</bndbox>
	</object>
	<object>
		<name>5</name>
		<pose>Unspecified</pose>
		<truncated>0</truncated>
		<difficult>0</difficult>
		<bndbox>
			<xmin>1316</xmin>
			<ymin>1293</ymin>
			<xmax>1582</xmax>
			<ymax>1618</ymax>
		</bndbox>
	</object>
	<object>
		<name>32</name>
		<pose>Unspecified</pose>
		<truncated>0</truncated>
		<difficult>0</difficult>
		<bndbox>
			<xmin>1545</xmin>
			<ymin>1124</ymin>
			<xmax>1809</xmax>
			<ymax>1384</ymax>
		</bndbox>
	</object>
	<object>
		<name>23</name>
		<pose>Unspecified</pose>
		<truncated>0</truncated>
		<difficult>0</difficult>
		<bndbox>
			<xmin>2130</xmin>
			<ymin>709</ymin>
			<xmax>2374</xmax>
			<ymax>914</ymax>
		</bndbox>
	</object>
	<object>
		<name>x</name>
		<pose>Unspecified</pose>
		<truncated>0</truncated>
		<difficult>0</difficult>
		<bndbox>
			<xmin>1751</xmin>
			<ymin>1162</ymin>
			<xmax>2011</xmax>
			<ymax>1545</ymax>
		</bndbox>
	</object>
	<object>
		<name>32</name>
		<pose>Unspecified</pose>
		<truncated>0</truncated>
		<difficult>0</difficult>
		<bndbox>
			<xmin>2174</xmin>
			<ymin>1395</ymin>
			<xmax>2372</xmax>
			<ymax>1572</ymax>
		</bndbox>
	</object>
</annotation>
