<annotation>
	<folder>JPEGImage</folder>
	<filename>lv2021-05-12-28.jpg</filename>
	<path>D:\cellproject\CELL\normal\2021-05-12\reorganize\JPEGImage\lv2021-05-12-28.jpg</path>
	<source>
		<database>Unknown</database>
	</source>
	<size>
		<width>2448</width>
		<height>2048</height>
		<depth>3</depth>
	</size>
	<segmented>0</segmented>
	<object>
		<name>6</name>
		<pose>Unspecified</pose>
		<truncated>0</truncated>
		<difficult>0</difficult>
		<bndbox>
			<xmin>112</xmin>
			<ymin>801</ymin>
			<xmax>313</xmax>
			<ymax>1045</ymax>
		</bndbox>
	</object>
	<object>
		<name>6</name>
		<pose>Unspecified</pose>
		<truncated>0</truncated>
		<difficult>0</difficult>
		<bndbox>
			<xmin>1882</xmin>
			<ymin>919</ymin>
			<xmax>2104</xmax>
			<ymax>1173</ymax>
		</bndbox>
	</object>
	<object>
		<name>32</name>
		<pose>Unspecified</pose>
		<truncated>0</truncated>
		<difficult>0</difficult>
		<bndbox>
			<xmin>2131</xmin>
			<ymin>320</ymin>
			<xmax>2282</xmax>
			<ymax>455</ymax>
		</bndbox>
	</object>
</annotation>
