<annotation>
	<folder>JPEGImages</folder>
	<filename>lv20210305-27.jpg</filename>
	<path>D:\细胞项目\CELL\normal\2021-03-06\reorganize\JPEGImages\lv20210305-27.jpg</path>
	<source>
		<database>Unknown</database>
	</source>
	<size>
		<width>2448</width>
		<height>2048</height>
		<depth>3</depth>
	</size>
	<segmented>0</segmented>
	<object>
		<name>3</name>
		<pose>Unspecified</pose>
		<truncated>0</truncated>
		<difficult>0</difficult>
		<bndbox>
			<xmin>686</xmin>
			<ymin>328</ymin>
			<xmax>950</xmax>
			<ymax>625</ymax>
		</bndbox>
	</object>
	<object>
		<name>32</name>
		<pose>Unspecified</pose>
		<truncated>0</truncated>
		<difficult>0</difficult>
		<bndbox>
			<xmin>279</xmin>
			<ymin>1348</ymin>
			<xmax>392</xmax>
			<ymax>1459</ymax>
		</bndbox>
	</object>
	<object>
		<name>2</name>
		<pose>Unspecified</pose>
		<truncated>0</truncated>
		<difficult>0</difficult>
		<bndbox>
			<xmin>481</xmin>
			<ymin>1477</ymin>
			<xmax>883</xmax>
			<ymax>1834</ymax>
		</bndbox>
	</object>
	<object>
		<name>3</name>
		<pose>Unspecified</pose>
		<truncated>0</truncated>
		<difficult>0</difficult>
		<bndbox>
			<xmin>766</xmin>
			<ymin>1700</ymin>
			<xmax>1058</xmax>
			<ymax>1985</ymax>
		</bndbox>
	</object>
	<object>
		<name>3</name>
		<pose>Unspecified</pose>
		<truncated>0</truncated>
		<difficult>0</difficult>
		<bndbox>
			<xmin>1632</xmin>
			<ymin>1065</ymin>
			<xmax>1968</xmax>
			<ymax>1310</ymax>
		</bndbox>
	</object>
	<object>
		<name>23</name>
		<pose>Unspecified</pose>
		<truncated>0</truncated>
		<difficult>0</difficult>
		<bndbox>
			<xmin>1730</xmin>
			<ymin>645</ymin>
			<xmax>1979</xmax>
			<ymax>908</ymax>
		</bndbox>
	</object>
	<object>
		<name>32</name>
		<pose>Unspecified</pose>
		<truncated>0</truncated>
		<difficult>0</difficult>
		<bndbox>
			<xmin>2095</xmin>
			<ymin>1017</ymin>
			<xmax>2228</xmax>
			<ymax>1185</ymax>
		</bndbox>
	</object>
	<object>
		<name>x</name>
		<pose>Unspecified</pose>
		<truncated>0</truncated>
		<difficult>0</difficult>
		<bndbox>
			<xmin>597</xmin>
			<ymin>821</ymin>
			<xmax>839</xmax>
			<ymax>1223</ymax>
		</bndbox>
	</object>
	<object>
		<name>x</name>
		<pose>Unspecified</pose>
		<truncated>0</truncated>
		<difficult>0</difficult>
		<bndbox>
			<xmin>1368</xmin>
			<ymin>483</ymin>
			<xmax>1581</xmax>
			<ymax>683</ymax>
		</bndbox>
	</object>
</annotation>
