<annotation>
	<folder>JPEGImages</folder>
	<filename>19.jpg</filename>
	<path>F:\大创相关\嗜酸2.2022.03.10\新建文件夹\JPEGImages\19.jpg</path>
	<source>
		<database>Unknown</database>
	</source>
	<size>
		<width>2448</width>
		<height>2048</height>
		<depth>3</depth>
	</size>
	<segmented>0</segmented>
	<object>
		<name>E2</name>
		<pose>Unspecified</pose>
		<truncated>0</truncated>
		<difficult>0</difficult>
		<bndbox>
			<xmin>545</xmin>
			<ymin>808</ymin>
			<xmax>812</xmax>
			<ymax>1089</ymax>
		</bndbox>
	</object>
	<object>
		<name>E2</name>
		<pose>Unspecified</pose>
		<truncated>0</truncated>
		<difficult>0</difficult>
		<bndbox>
			<xmin>1232</xmin>
			<ymin>921</ymin>
			<xmax>1492</xmax>
			<ymax>1193</ymax>
		</bndbox>
	</object>
</annotation>
