<annotation>
	<folder>JPEGImage</folder>
	<filename>yuan2021-06-24-42.jpg</filename>
	<path>C:\Users\13676\Desktop\2021-06-24\reorganize\JPEGImage\yuan2021-06-24-42.jpg</path>
	<source>
		<database>Unknown</database>
	</source>
	<size>
		<width>2448</width>
		<height>2048</height>
		<depth>3</depth>
	</size>
	<segmented>0</segmented>
	<object>
		<name>24</name>
		<pose>Unspecified</pose>
		<truncated>0</truncated>
		<difficult>0</difficult>
		<bndbox>
			<xmin>74</xmin>
			<ymin>648</ymin>
			<xmax>241</xmax>
			<ymax>782</ymax>
		</bndbox>
	</object>
	<object>
		<name>24</name>
		<pose>Unspecified</pose>
		<truncated>0</truncated>
		<difficult>0</difficult>
		<bndbox>
			<xmin>152</xmin>
			<ymin>787</ymin>
			<xmax>300</xmax>
			<ymax>956</ymax>
		</bndbox>
	</object>
	<object>
		<name>24</name>
		<pose>Unspecified</pose>
		<truncated>0</truncated>
		<difficult>0</difficult>
		<bndbox>
			<xmin>243</xmin>
			<ymin>884</ymin>
			<xmax>430</xmax>
			<ymax>1045</ymax>
		</bndbox>
	</object>
	<object>
		<name>32</name>
		<pose>Unspecified</pose>
		<truncated>0</truncated>
		<difficult>0</difficult>
		<bndbox>
			<xmin>527</xmin>
			<ymin>1199</ymin>
			<xmax>666</xmax>
			<ymax>1364</ymax>
		</bndbox>
	</object>
	<object>
		<name>5</name>
		<pose>Unspecified</pose>
		<truncated>0</truncated>
		<difficult>0</difficult>
		<bndbox>
			<xmin>1792</xmin>
			<ymin>1391</ymin>
			<xmax>2000</xmax>
			<ymax>1607</ymax>
		</bndbox>
	</object>
	<object>
		<name>32</name>
		<pose>Unspecified</pose>
		<truncated>0</truncated>
		<difficult>0</difficult>
		<bndbox>
			<xmin>2031</xmin>
			<ymin>1224</ymin>
			<xmax>2187</xmax>
			<ymax>1395</ymax>
		</bndbox>
	</object>
</annotation>
