<annotation>
	<folder>JPEGImage</folder>
	<filename>yuan2021-08-27-21.jpg</filename>
	<path>F:\大创相关\2021-08-27\2021-08-27\reorganize\JPEGImage\yuan2021-08-27-21.jpg</path>
	<source>
		<database>Unknown</database>
	</source>
	<size>
		<width>2448</width>
		<height>2048</height>
		<depth>3</depth>
	</size>
	<segmented>0</segmented>
	<object>
		<name>5</name>
		<pose>Unspecified</pose>
		<truncated>0</truncated>
		<difficult>0</difficult>
		<bndbox>
			<xmin>736</xmin>
			<ymin>241</ymin>
			<xmax>951</xmax>
			<ymax>465</ymax>
		</bndbox>
	</object>
	<object>
		<name>4</name>
		<pose>Unspecified</pose>
		<truncated>0</truncated>
		<difficult>0</difficult>
		<bndbox>
			<xmin>332</xmin>
			<ymin>891</ymin>
			<xmax>558</xmax>
			<ymax>1123</ymax>
		</bndbox>
	</object>
	<object>
		<name>23</name>
		<pose>Unspecified</pose>
		<truncated>0</truncated>
		<difficult>0</difficult>
		<bndbox>
			<xmin>519</xmin>
			<ymin>1050</ymin>
			<xmax>740</xmax>
			<ymax>1265</ymax>
		</bndbox>
	</object>
	<object>
		<name>32</name>
		<pose>Unspecified</pose>
		<truncated>0</truncated>
		<difficult>0</difficult>
		<bndbox>
			<xmin>821</xmin>
			<ymin>971</ymin>
			<xmax>979</xmax>
			<ymax>1136</ymax>
		</bndbox>
	</object>
	<object>
		<name>5</name>
		<pose>Unspecified</pose>
		<truncated>0</truncated>
		<difficult>0</difficult>
		<bndbox>
			<xmin>1451</xmin>
			<ymin>1143</ymin>
			<xmax>1710</xmax>
			<ymax>1373</ymax>
		</bndbox>
	</object>
	<object>
		<name>3</name>
		<pose>Unspecified</pose>
		<truncated>0</truncated>
		<difficult>0</difficult>
		<bndbox>
			<xmin>305</xmin>
			<ymin>1613</ymin>
			<xmax>551</xmax>
			<ymax>1860</ymax>
		</bndbox>
	</object>
	<object>
		<name>6</name>
		<pose>Unspecified</pose>
		<truncated>0</truncated>
		<difficult>0</difficult>
		<bndbox>
			<xmin>1060</xmin>
			<ymin>1652</ymin>
			<xmax>1282</xmax>
			<ymax>1871</ymax>
		</bndbox>
	</object>
</annotation>
